{"regressor": [["linear_model", "ARDRegression", {"normalize": false, "n_iter": 300, "verbose": false, "lambda_1": 1e-06, "lambda_2": 1e-06, "fit_intercept": true, "threshold_lambda": 10000.0, "alpha_2": 1e-06, "tol": 0.001, "alpha_1": 1e-06, "copy_X": true, "compute_score": false}], ["linear_model", "BayesianRidge", {"normalize": false, "n_iter": 300, "verbose": false, "lambda_1": 1e-06, "lambda_2": 1e-06, "fit_intercept": true, "alpha_2": 1e-06, "tol": 0.001, "alpha_1": 1e-06, "copy_X": true, "compute_score": false}], ["linear_model", "ElasticNet", {"normalize": false, "warm_start": false, "selection": "cyclic", "fit_intercept": true, "l1_ratio": 0.5, "max_iter": 1000, "precompute": false, "random_state": null, "tol": 0.0001, "positive": false, "copy_X": true, "alpha": 1.0}], ["linear_model", "ElasticNetCV", {"normalize": false, "alphas": null, "n_jobs": 1, "verbose": 0, "fit_intercept": true, "selection": "cyclic", "l1_ratio": 0.5, "n_alphas": 100, "max_iter": 1000, "eps": 0.001, "precompute": "auto", "random_state": null, "tol": 0.0001, "positive": false, "copy_X": true, "cv": null}], ["linear_model", "Lars", {"n_nonzero_coefs": 500, "normalize": true, "fit_path": true, "fit_intercept": true, "positive": false, "eps": 2.2204460492503131e-16, "precompute": "auto", "copy_X": true, "verbose": false}], ["linear_model", "LarsCV", {"normalize": true, "n_jobs": 1, "verbose": false, "fit_intercept": true, "positive": false, "max_iter": 500, "eps": 2.2204460492503131e-16, "precompute": "auto", "max_n_alphas": 1000, "copy_X": true, "cv": null}], ["linear_model", "Lasso", {"normalize": false, "warm_start": false, "selection": "cyclic", "fit_intercept": true, "positive": false, "max_iter": 1000, "precompute": false, "random_state": null, "tol": 0.0001, "copy_X": true, "alpha": 1.0}], ["linear_model", "LassoCV", {"normalize": false, "alphas": null, "n_jobs": 1, "verbose": false, "fit_intercept": true, "selection": "cyclic", "positive": false, "n_alphas": 100, "max_iter": 1000, "eps": 0.001, "precompute": "auto", "random_state": null, "tol": 0.0001, "copy_X": true, "cv": null}], ["linear_model", "LassoLars", {"normalize": true, "fit_path": true, "fit_intercept": true, "positive": false, "max_iter": 500, "eps": 2.2204460492503131e-16, "precompute": "auto", "copy_X": true, "alpha": 1.0, "verbose": false}], ["linear_model", "LassoLarsCV", {"normalize": true, "n_jobs": 1, "verbose": false, "fit_intercept": true, "positive": false, "max_iter": 500, "eps": 2.2204460492503131e-16, "precompute": "auto", "max_n_alphas": 1000, "copy_X": true, "cv": null}], ["linear_model", "LassoLarsIC", {"normalize": true, "verbose": false, "fit_intercept": true, "positive": false, "max_iter": 500, "eps": 2.2204460492503131e-16, "precompute": "auto", "criterion": "aic", "copy_X": true}], ["linear_model", "LinearRegression", {"copy_X": true, "normalize": false, "n_jobs": 1, "fit_intercept": true}], ["linear_model", "MultiTaskElasticNet", {"normalize": false, "warm_start": false, "selection": "cyclic", "fit_intercept": true, "l1_ratio": 0.5, "max_iter": 1000, "random_state": null, "tol": 0.0001, "copy_X": true, "alpha": 1.0}], ["linear_model", "MultiTaskElasticNetCV", {"normalize": false, "alphas": null, "n_jobs": 1, "verbose": 0, "fit_intercept": true, "selection": "cyclic", "l1_ratio": 0.5, "n_alphas": 100, "max_iter": 1000, "eps": 0.001, "random_state": null, "tol": 0.0001, "copy_X": true, "cv": null}], ["linear_model", "MultiTaskLasso", {"normalize": false, "warm_start": false, "selection": "cyclic", "fit_intercept": true, "max_iter": 1000, "random_state": null, "tol": 0.0001, "copy_X": true, "alpha": 1.0}], ["linear_model", "MultiTaskLassoCV", {"normalize": false, "alphas": null, "n_jobs": 1, "verbose": false, "fit_intercept": true, "selection": "cyclic", "n_alphas": 100, "max_iter": 1000, "eps": 0.001, "random_state": null, "tol": 0.0001, "copy_X": true, "cv": null}], ["linear_model", "OrthogonalMatchingPursuit", {"n_nonzero_coefs": null, "normalize": true, "tol": null, "precompute": "auto", "fit_intercept": true}], ["linear_model", "OrthogonalMatchingPursuitCV", {"normalize": true, "n_jobs": 1, "verbose": false, "fit_intercept": true, "max_iter": null, "copy": true, "cv": null}], ["linear_model", "PassiveAggressiveRegressor", {"warm_start": false, "n_iter": 5, "C": 1.0, "shuffle": true, "verbose": 0, "loss": "epsilon_insensitive", "epsilon": 0.1, "fit_intercept": true, "random_state": null}], ["linear_model", "RANSACRegressor", {"base_estimator": null, "residual_metric": null, "is_model_valid": null, "stop_n_inliers": Infinity, "stop_score": Infinity, "max_trials": 100, "random_state": null, "stop_probability": 0.99, "residual_threshold": null, "min_samples": null, "is_data_valid": null}], ["linear_model", "Ridge", {"normalize": false, "fit_intercept": true, "max_iter": null, "random_state": null, "tol": 0.001, "copy_X": true, "alpha": 1.0, "solver": "auto"}], ["linear_model", "RidgeCV", {"normalize": false, "alphas": [0.1, 1.0, 10.0], "fit_intercept": true, "gcv_mode": null, "store_cv_values": false, "scoring": null, "cv": null}], ["linear_model", "SGDRegressor", {"warm_start": false, "loss": "squared_loss", "eta0": 0.01, "verbose": 0, "shuffle": true, "fit_intercept": true, "l1_ratio": 0.15, "average": false, "n_iter": 5, "penalty": "l2", "power_t": 0.25, "random_state": null, "epsilon": 0.1, "alpha": 0.0001, "learning_rate": "invscaling"}], ["linear_model", "TheilSenRegressor", {"n_jobs": 1, "tol": 0.001, "fit_intercept": true, "max_iter": 300, "random_state": null, "n_subsamples": null, "copy_X": true, "max_subpopulation": 10000, "verbose": false}], ["ensemble", "AdaBoostRegressor", {"n_estimators": 50, "loss": "linear", "base_estimator": null, "random_state": null, "learning_rate": 1.0}], ["ensemble", "BaggingRegressor", {"warm_start": false, "max_samples": 1.0, "base_estimator": null, "n_jobs": 1, "verbose": 0, "bootstrap": true, "oob_score": false, "n_estimators": 10, "random_state": null, "max_features": 1.0, "bootstrap_features": false}], ["ensemble", "ExtraTreesRegressor", {"warm_start": false, "oob_score": false, "n_jobs": 1, "verbose": 0, "max_leaf_nodes": null, "bootstrap": false, "min_samples_leaf": 1, "n_estimators": 10, "min_samples_split": 2, "min_weight_fraction_leaf": 0.0, "criterion": "mse", "random_state": null, "max_features": "auto", "max_depth": null}], ["ensemble", "GradientBoostingRegressor", {"presort": "auto", "loss": "ls", "verbose": 0, "subsample": 1.0, "max_leaf_nodes": null, "learning_rate": 0.1, "warm_start": false, "min_samples_leaf": 1, "n_estimators": 100, "min_samples_split": 2, "init": null, "min_weight_fraction_leaf": 0.0, "random_state": null, "max_features": null, "alpha": 0.9, "max_depth": 3}], ["ensemble", "RandomForestRegressor", {"warm_start": false, "oob_score": false, "n_jobs": 1, "verbose": 0, "max_leaf_nodes": null, "bootstrap": true, "min_samples_leaf": 1, "n_estimators": 10, "min_samples_split": 2, "min_weight_fraction_leaf": 0.0, "criterion": "mse", "random_state": null, "max_features": "auto", "max_depth": null}], ["svm", "LinearSVR", {"loss": "epsilon_insensitive", "C": 1.0, "intercept_scaling": 1.0, "fit_intercept": true, "epsilon": 0.0, "max_iter": 1000, "random_state": null, "dual": true, "tol": 0.0001, "verbose": 0}], ["svm", "NuSVR", {"kernel": "rbf", "C": 1.0, "verbose": false, "degree": 3, "shrinking": true, "max_iter": -1, "tol": 0.001, "cache_size": 200, "coef0": 0.0, "nu": 0.5, "gamma": "auto"}], ["svm", "SVR", {"kernel": "rbf", "C": 1.0, "verbose": false, "degree": 3, "epsilon": 0.1, "shrinking": true, "max_iter": -1, "tol": 0.001, "cache_size": 200, "coef0": 0.0, "gamma": "auto"}], ["neighbors", "KNeighborsRegressor", {"n_neighbors": 5, "n_jobs": 1, "algorithm": "auto", "metric": "minkowski", "metric_params": null, "p": 2, "weights": "uniform", "leaf_size": 30}], ["neighbors", "RadiusNeighborsRegressor", {"algorithm": "auto", "metric": "minkowski", "metric_params": null, "p": 2, "radius": 1.0, "leaf_size": 30, "weights": "uniform"}]], "classifier": [["linear_model", "LogisticRegression", {"warm_start": false, "C": 1.0, "n_jobs": 1, "verbose": 0, "intercept_scaling": 1, "fit_intercept": true, "max_iter": 100, "penalty": "l2", "multi_class": "ovr", "random_state": null, "dual": false, "tol": 0.0001, "solver": "liblinear", "class_weight": null}], ["linear_model", "LogisticRegressionCV", {"scoring": null, "n_jobs": 1, "verbose": 0, "intercept_scaling": 1.0, "fit_intercept": true, "max_iter": 100, "refit": true, "penalty": "l2", "multi_class": "ovr", "random_state": null, "dual": false, "tol": 0.0001, "Cs": 10, "solver": "lbfgs", "cv": null, "class_weight": null}], ["linear_model", "PassiveAggressiveClassifier", {"warm_start": false, "n_iter": 5, "C": 1.0, "n_jobs": 1, "shuffle": true, "verbose": 0, "loss": "hinge", "fit_intercept": true, "random_state": null, "class_weight": null}], ["linear_model", "Perceptron", {"warm_start": false, "n_iter": 5, "n_jobs": 1, "eta0": 1.0, "verbose": 0, "shuffle": true, "fit_intercept": true, "penalty": null, "random_state": 0, "alpha": 0.0001, "class_weight": null}], ["linear_model", "RidgeClassifier", {"normalize": false, "fit_intercept": true, "max_iter": null, "random_state": null, "tol": 0.001, "copy_X": true, "alpha": 1.0, "solver": "auto", "class_weight": null}], ["linear_model", "RidgeClassifierCV", {"normalize": false, "alphas": [0.1, 1.0, 10.0], "fit_intercept": true, "scoring": null, "cv": null, "class_weight": null}], ["linear_model", "SGDClassifier", {"warm_start": false, "loss": "hinge", "n_jobs": 1, "eta0": 0.0, "verbose": 0, "shuffle": true, "fit_intercept": true, "epsilon": 0.1, "average": false, "n_iter": 5, "penalty": "l2", "power_t": 0.5, "random_state": null, "l1_ratio": 0.15, "alpha": 0.0001, "learning_rate": "optimal", "class_weight": null}], ["ensemble", "AdaBoostClassifier", {"n_estimators": 50, "base_estimator": null, "random_state": null, "learning_rate": 1.0, "algorithm": "SAMME.R"}], ["ensemble", "BaggingClassifier", {"warm_start": false, "max_samples": 1.0, "base_estimator": null, "n_jobs": 1, "verbose": 0, "bootstrap": true, "oob_score": false, "n_estimators": 10, "random_state": null, "max_features": 1.0, "bootstrap_features": false}], ["ensemble", "ExtraTreesClassifier", {"warm_start": false, "oob_score": false, "n_jobs": 1, "verbose": 0, "max_leaf_nodes": null, "bootstrap": false, "min_samples_leaf": 1, "n_estimators": 10, "min_samples_split": 2, "min_weight_fraction_leaf": 0.0, "criterion": "gini", "random_state": null, "max_features": "auto", "max_depth": null, "class_weight": null}], ["ensemble", "GradientBoostingClassifier", {"presort": "auto", "loss": "deviance", "verbose": 0, "subsample": 1.0, "max_leaf_nodes": null, "learning_rate": 0.1, "warm_start": false, "min_samples_leaf": 1, "n_estimators": 100, "min_samples_split": 2, "init": null, "min_weight_fraction_leaf": 0.0, "random_state": null, "max_features": null, "max_depth": 3}], ["ensemble", "RandomForestClassifier", {"warm_start": false, "oob_score": false, "n_jobs": 1, "verbose": 0, "max_leaf_nodes": null, "bootstrap": true, "min_samples_leaf": 1, "n_estimators": 10, "min_samples_split": 2, "min_weight_fraction_leaf": 0.0, "criterion": "gini", "random_state": null, "max_features": "auto", "max_depth": null, "class_weight": null}], ["svm", "LinearSVC", {"loss": "squared_hinge", "C": 1.0, "verbose": 0, "intercept_scaling": 1, "fit_intercept": true, "max_iter": 1000, "penalty": "l2", "multi_class": "ovr", "random_state": null, "dual": true, "tol": 0.0001, "class_weight": null}], ["svm", "NuSVC", {"kernel": "rbf", "verbose": false, "probability": false, "degree": 3, "shrinking": true, "max_iter": -1, "decision_function_shape": null, "random_state": null, "tol": 0.001, "cache_size": 200, "coef0": 0.0, "nu": 0.5, "gamma": "auto", "class_weight": null}], ["svm", "SVC", {"kernel": "rbf", "C": 1.0, "verbose": false, "probability": false, "degree": 3, "shrinking": true, "max_iter": -1, "decision_function_shape": null, "random_state": null, "tol": 0.001, "cache_size": 200, "coef0": 0.0, "gamma": "auto", "class_weight": null}], ["neighbors", "KNeighborsClassifier", {"n_neighbors": 5, "n_jobs": 1, "algorithm": "auto", "metric": "minkowski", "metric_params": null, "p": 2, "weights": "uniform", "leaf_size": 30}], ["neighbors", "NearestCentroid", {"metric": "euclidean", "shrink_threshold": null}], ["neighbors", "RadiusNeighborsClassifier", {"algorithm": "auto", "metric": "minkowski", "metric_params": null, "p": 2, "radius": 1.0, "leaf_size": 30, "weights": "uniform", "outlier_label": null}]]}